<?xml version="1.0" encoding="UTF-8"?>

<ProfileSlicing xmlns:xsi="http://www.w3.org/2001/XMLSchema-instance" ID="67bc85d8e4b0a4d607a8f397_675b1d62e4b06103017974b5_S" xsi:noNamespaceSchemaLocation="https://raw.githubusercontent.com/usnistgov/hl7-v2-schemas/1.7.2/src/main/resources/hl7-v2-schemas/ProfileSlicing.xsd">
  <FieldSlicing>
    <SegmentContext ID="PID_SS02">
      <OccurrenceSlicing Position="5">
        <Slice Occurrence="1" Ref="XPN_SS_L"/>
        <Slice Occurrence="2" Ref="XPN_SS_SU"/>
      </OccurrenceSlicing>
    </SegmentContext>
    <SegmentContext ID="PID_SS01">
      <OccurrenceSlicing Position="5">
        <Slice Occurrence="1" Ref="XPN_SS_L"/>
        <Slice Occurrence="2" Ref="XPN_SS_SU"/>
      </OccurrenceSlicing>
    </SegmentContext>
  </FieldSlicing>
</ProfileSlicing>
